{
	"editor": {
		"backDropShape": "item/tool/fishing/hook-metal",
		"allAngles": true,
		"entityTextureMode": false
	},
	"textureWidth": 8,
	"textureHeight": 8,
	"textureSizes": {
		"fill-earthworm-bacon.png": [8, 8]
	},
	"textures": {
	},
	"elements": [
		{
			"name": "wormbacon",
			"from": [0, 0, 0],
			"to": [0, 0, 0],
			"rotationOrigin": [0, 0, 0],
			"children": [
				{
					"name": "upper",
					"from": [2, 0, -0.7],
					"to": [2, 0, -0.7],
					"rotationOrigin": [2, 0, -0.7],
					"children": [
						{
							"name": "wormpart1",
							"from": [0.6022, 0.0001, 0.1246],
							"to": [2.1022, 0.4001, 0.7246],
							"rotationOrigin": [0.7, 0, 0.8],
							"faces": {
								"north": {"texture": "#fill-earthworm-bacon.png", "uv": [5.5, 4, 7, 4.4], "autoUv": false, "snapUv": false},
								"east": {"texture": "#fill-earthworm-bacon.png", "uv": [3.25, 1, 3.85, 1.4], "autoUv": false, "snapUv": false},
								"south": {"texture": "#fill-earthworm-bacon.png", "uv": [1.75, 1.25, 3.25, 1.65], "autoUv": false, "snapUv": false},
								"west": {"texture": "#fill-earthworm-bacon.png", "uv": [5.25, 2.25, 5.85, 2.65], "autoUv": false, "snapUv": false},
								"up": {"texture": "#fill-earthworm-bacon.png", "uv": [4.5, 1, 6, 1.6], "rotation": 180, "autoUv": false, "snapUv": false},
								"down": {"texture": "#fill-earthworm-bacon.png", "uv": [2.5, 4.75, 3.1, 6.25], "rotation": 90, "autoUv": false, "snapUv": false}
							},
							"rotationX": 0.0608,
							"rotationY": 70,
							"rotationZ": -0.1549,
							"shade": false
						},
						{
							"name": "wormpart2",
							"from": [-2.0389, -0.0079, 1.1826],
							"to": [-0.5389, 0.3921, 1.7826],
							"rotationOrigin": [-0.7, 0, 1.3],
							"faces": {
								"north": {"texture": "#fill-earthworm-bacon.png", "uv": [6, 4.85, 7.5, 5.25], "autoUv": false, "snapUv": false},
								"east": {"texture": "#fill-earthworm-bacon.png", "uv": [5, 5, 5.6, 5.4], "autoUv": false, "snapUv": false},
								"south": {"texture": "#fill-earthworm-bacon.png", "uv": [3.75, 5.75, 5.25, 6.15], "autoUv": false, "snapUv": false},
								"west": {"texture": "#fill-earthworm-bacon.png", "uv": [2, 3.25, 2.6, 3.65], "autoUv": false, "snapUv": false},
								"up": {"texture": "#fill-earthworm-bacon.png", "uv": [2.5, 4.15, 4, 4.75], "autoUv": false, "snapUv": false},
								"down": {"texture": "#fill-earthworm-bacon.png", "uv": [1, 0.15, 2.5, 0.75], "autoUv": false, "snapUv": false}
							},
							"rotationX": 179.9355,
							"rotationY": -21,
							"rotationZ": -179.9432,
							"shade": false
						},
						{
							"name": "wormpart3",
							"from": [-3.3, 0, 0.9],
							"to": [-1.8, 0.4, 1.5],
							"rotationOrigin": [-2, 0, 0.9],
							"faces": {
								"north": {"texture": "#fill-earthworm-bacon.png", "uv": [4.65, 0.5, 4.25, 2], "rotation": 270, "autoUv": false, "snapUv": false},
								"east": {"texture": "#fill-earthworm-bacon.png", "uv": [1.75, 3.5, 2.15, 4.1], "rotation": 270, "autoUv": false, "snapUv": false},
								"south": {"texture": "#fill-earthworm-bacon.png", "uv": [6.25, 6.5, 6.65, 8], "rotation": 90, "autoUv": false, "snapUv": false},
								"west": {"texture": "#fill-earthworm-bacon.png", "uv": [3.25, 1.5, 3.65, 2.1], "rotation": 270, "autoUv": false, "snapUv": false},
								"up": {"texture": "#fill-earthworm-bacon.png", "uv": [3.6, 3.75, 3, 2.25], "rotation": 270, "autoUv": false, "snapUv": false},
								"down": {"texture": "#fill-earthworm-bacon.png", "uv": [3.35, 3.75, 2.75, 2.25], "rotation": 90, "autoUv": false, "snapUv": false}
							},
							"rotationX": 0.1,
							"rotationY": 156.5,
							"shade": false
						}
					]
				},
				{
					"name": "lower",
					"from": [0, 0, -0.35],
					"to": [0, 0, -0.35],
					"rotationOrigin": [0, 0, -0.35],
					"rotationY": 46,
					"children": [
						{
							"name": "wormpart1",
							"from": [-4.1217, -0.0098, -0.15],
							"to": [-2.6217, 0.3902, 0.45],
							"rotationOrigin": [-2.7, 0, -0.1],
							"faces": {
								"north": {"texture": "#fill-earthworm-bacon.png", "uv": [2.75, 2, 4.25, 2.4], "rotation": 180, "autoUv": false, "snapUv": false},
								"east": {"texture": "#fill-earthworm-bacon.png", "uv": [2.25, 2, 2.85, 2.4], "autoUv": false, "snapUv": false},
								"south": {"texture": "#fill-earthworm-bacon.png", "uv": [6.5, 5.25, 8, 5.65], "rotation": 180, "autoUv": false, "snapUv": false},
								"west": {"texture": "#fill-earthworm-bacon.png", "uv": [3, 1.25, 3.6, 1.65], "autoUv": false, "snapUv": false},
								"up": {"texture": "#fill-earthworm-bacon.png", "uv": [8, 2.6, 6.5, 2], "autoUv": false, "snapUv": false},
								"down": {"texture": "#fill-earthworm-bacon.png", "uv": [5.5, 1.6, 4, 1], "autoUv": false, "snapUv": false}
							},
							"rotationX": 0.003,
							"rotationY": 70,
							"rotationZ": 0.0976,
							"shade": false
						},
						{
							"name": "wormpart2",
							"from": [-1.5611, 0.0021, -0.9826],
							"to": [-0.0611, 0.4021, -0.3826],
							"rotationOrigin": [-1.4, 0, -0.5],
							"faces": {
								"north": {"texture": "#fill-earthworm-bacon.png", "uv": [6, 0.25, 6.4, 1.75], "rotation": 270, "autoUv": false, "snapUv": false},
								"east": {"texture": "#fill-earthworm-bacon.png", "uv": [2.5, 2.5, 3.1, 2.9], "autoUv": false, "snapUv": false},
								"south": {"texture": "#fill-earthworm-bacon.png", "uv": [5, 5.25, 5.4, 6.75], "rotation": 270, "autoUv": false, "snapUv": false},
								"west": {"texture": "#fill-earthworm-bacon.png", "uv": [3.5, 3.5, 4.1, 3.9], "autoUv": false, "snapUv": false},
								"up": {"texture": "#fill-earthworm-bacon.png", "uv": [6.75, 2.1, 5.25, 1.5], "autoUv": false, "snapUv": false},
								"down": {"texture": "#fill-earthworm-bacon.png", "uv": [2.5, 5.6, 1, 5], "autoUv": false, "snapUv": false}
							},
							"rotationX": -179.9367,
							"rotationY": -18,
							"rotationZ": 179.9397,
							"shade": false
						},
						{
							"name": "wormpart3",
							"from": [-0.3, -0.01, -0.7],
							"to": [1.2, 0.39, -0.1],
							"rotationOrigin": [-0.1, 0, -0.1],
							"faces": {
								"north": {"texture": "#fill-earthworm-bacon.png", "uv": [1.25, 3, 1.65, 4.5], "rotation": 90, "autoUv": false, "snapUv": false},
								"east": {"texture": "#fill-earthworm-bacon.png", "uv": [2, 0, 2.6, 0.4], "autoUv": false, "snapUv": false},
								"south": {"texture": "#fill-earthworm-bacon.png", "uv": [5.5, 3.75, 7, 4.15], "autoUv": false, "snapUv": false},
								"west": {"texture": "#fill-earthworm-bacon.png", "uv": [2.25, 1, 2.85, 1.4], "autoUv": false, "snapUv": false},
								"up": {"texture": "#fill-earthworm-bacon.png", "uv": [2.75, 2.5, 3.35, 4], "rotation": 270, "autoUv": false, "snapUv": false},
								"down": {"texture": "#fill-earthworm-bacon.png", "uv": [4.5, 1, 6, 1.6], "rotation": 180, "autoUv": false, "snapUv": false}
							},
							"rotationX": -0.1,
							"rotationY": 155.5,
							"shade": false
						}
					]
				}
			]
		}
	],
	"animations": []
}